{
    "Maleo": "ID",
    "Sumatran Partridge": "ID",
    "Chestnut-bellied Partridge": "ID",
    "Red-billed Partridge": "ID",
    "Snow Mountain Quail": "ID",
    "Green Junglefowl": "ID",
    "Salvadori's Pheasant": "ID",
    "Sombre Pigeon": "ID",
    "Javan Frogmouth": "ID",
    "Mees's Nightjar": "ID",
    "Sulawesi Nightjar": "ID",
    "Salvadori's Nightjar": "ID",
    "Moluccan Owlet-nightjar": "ID",
    "Cave Swiftlet": "ID",
    "Tenggara Swiftlet": "ID",
    "Volcano Swiftlet": "ID",
    "Biak Coucal": "ID",
    "Bay Coucal": "ID",
    "Goliath Coucal": "ID",
    "Mentawai Malkoha": "ID",
    "Yellow-billed Malkoha": "ID",
    "Black-billed Koel": "ID",
    "Sulawesi Cuckoo": "ID",
    "Snoring Rail": "ID",
    "Blue-faced Rail": "ID",
    "Talaud Rail": "ID",
    "Isabelline Bush-hen": "ID",
    "Talaud Bush-hen": "ID",
    "Black-backed Swamphen": "ID",
    "Javan Lapwing": "ID",
    "Javan Woodcock": "ID",
    "Sulawesi Woodcock": "ID",
    "Moluccan Woodcock": "ID",
    "Sumba Buttonquail": "ID",
    "Sumba Boobook": "ID",
    "Rote Boobook": "ID",
    "Alor Boobook": "ID",
    "Least Boobook": "ID",
    "Togian Boobook": "ID",
    "Ochre-bellied Boobook": "ID",
    "Cinnabar Boobook": "ID",
    "Halmahera Boobook": "ID",
    "Buru Boobook": "ID",
    "Seram Boobook": "ID",
    "Tanimbar Boobook": "ID",
    "Speckled Boobook": "ID",
    "Javan Owlet": "ID",
    "Sulawesi Honey-buzzard": "ID",
    "Sulawesi Goshawk": "ID",
    "Spot-tailed Goshawk": "ID",
    "Moluccan Goshawk": "ID",
    "Rufous-necked Sparrowhawk": "ID",
    "Vinous-breasted Sparrowhawk": "ID",
    "Javan Trogon": "ID",
    "Sumatran Trogon": "ID",
    "Sulawesi Hornbill": "ID",
    "Knobbed Hornbill": "ID",
    "Sumba Hornbill": "ID",
    "Purple-bearded Bee-eater": "ID",
    "Purple-winged Roller": "ID",
    "Javan Blue-banded Kingfisher": "ID",
    "Javan Kingfisher": "ID",
    "White-rumped Kingfisher": "ID",
    "Scaly-breasted Kingfisher": "ID",
    "Blue-and-white Kingfisher": "ID",
    "Lazuli Kingfisher": "ID",
    "Sombre Kingfisher": "ID",
    "Talaud Kingfisher": "ID",
    "Sangihe Lilac Kingfisher": "ID",
    "Sulawesi Lilac Kingfisher": "ID",
    "Yellow-eared Barbet": "ID",
    "Black-banded Barbet": "ID",
    "Flame-fronted Barbet": "ID",
    "Brown-throated Barbet": "ID",
    "Javan Flameback": "ID",
    "Ashy Woodpecker": "ID",
    "Sulawesi Pygmy Woodpecker": "ID",
    "Tanimbar Corella": "ID",
    "Salmon-crested Cockatoo": "ID",
    "White Cockatoo": "ID",
    "Blue-fronted Lorikeet": "ID",
    "Chattering Lory": "ID",
    "Purple-naped Lory": "ID",
    "Black Lory": "ID",
    "Red-and-blue Lory": "ID",
    "Violet-necked Lory": "ID",
    "Red Lory": "ID",
    "Blue-streaked Lory": "ID",
    "Black-winged Lory": "ID",
    "Blue-eared Lory": "ID",
    "Ornate Lorikeet": "ID",
    "Biak Lorikeet": "ID",
    "Buru Racquet-tail": "ID",
    "Golden-mantled Racquet-tail": "ID",
    "Moluccan Eclectus": "ID",
    "Sumba Eclectus": "ID",
    "Tanimbar Eclectus": "ID",
    "Great-billed Parrot": "ID",
    "Black-lored Parrot": "ID",
    "Simeulue Parrot": "ID",
    "Sulawesi Pitta": "ID",
    "Sula Pitta": "ID",
    "North Moluccan Pitta": "ID",
    "South Moluccan Pitta": "ID",
    "Graceful Pitta": "ID",
    "Schneider's Pitta": "ID",
    "Biak Hooded Pitta": "ID",
    "Ivory-breasted Pitta": "ID",
    "White-eared Catbird": "ID",
    "Vogelkop Bowerbird": "ID",
    "Golden-fronted Bowerbird": "ID",
    "Dark-eared Myza": "ID",
    "White-eared Myza": "ID",
    "Olive Honeyeater": "ID",
    "Buru Honeyeater": "ID",
    "Seram Honeyeater": "ID",
    "White-streaked Friarbird": "ID",
    "Brass's Friarbird": "ID",
    "Seram Friarbird": "ID",
    "Tanimbar Friarbird": "ID",
    "Moluccan Myzomela": "ID",
    "Crimson-hooded Myzomela": "ID",
    "Alor Myzomela": "ID",
    "Sumba Myzomela": "ID",
    "Rote Myzomela": "ID",
    "Sulawesi Myzomela": "ID",
    "Bacan Myzomela": "ID",
    "Wakolo Myzomela": "ID",
    "Banda Myzomela": "ID",
    "Rufous-sided Honeyeater": "ID",
    "Arfak Honeyeater": "ID",
    "Foja Honeyeater": "ID",
    "Orange-cheeked Honeyeater": "ID",
    "Biak Gerygone": "ID",
    "Rufous-sided Gerygone": "ID",
    "Vogelkop Scrubwren": "ID",
    "Wetar Figbird": "ID",
    "Halmahera Oriole": "ID",
    "Seram Oriole": "ID",
    "Tanimbar Oriole": "ID",
    "Buru Oriole": "ID",
    "Javan Oriole": "ID",
    "Western Crested Berrypecker": "ID",
    "Maroon-backed Whistler": "ID",
    "Sangihe Whistler": "ID",
    "Bare-throated Whistler": "ID",
    "Vogelkop Whistler": "ID",
    "Sulphur-bellied Whistler": "ID",
    "Selayar Whistler": "ID",
    "Island Whistler": "ID",
    "Biak Whistler": "ID",
    "Wallacean Whistler": "ID",
    "Black-chinned Whistler": "ID",
    "Baliem Whistler": "ID",
    "Sunda Minivet": "ID",
    "Flores Minivet": "ID",
    "Cerulean Cuckooshrike": "ID",
    "Pied Cuckooshrike": "ID",
    "Buru Cuckooshrike": "ID",
    "Slaty Cuckooshrike": "ID",
    "White-rumped Cuckooshrike": "ID",
    "Moluccan Cuckooshrike": "ID",
    "Kai Cicadabird": "ID",
    "Pale Cicadabird": "ID",
    "Sulawesi Cicadabird": "ID",
    "Sula Cicadabird": "ID",
    "Obi Cicadabird": "ID",
    "Geelvink Cicadabird": "ID",
    "Pygmy Cuckooshrike": "ID",
    "Rufous-bellied Triller": "ID",
    "Biak Triller": "ID",
    "White-rumped Triller": "ID",
    "Ivory-backed Woodswallow": "ID",
    "White-bellied Fantail": "ID",
    "Cinnamon-tailed Fantail": "ID",
    "Brown-capped Fantail": "ID",
    "Rufous-tailed Fantail": "ID",
    "Sulawesi Fantail": "ID",
    "Taliabu Fantail": "ID",
    "Tawny-backed Fantail": "ID",
    "Long-tailed Fantail": "ID",
    "Sumatran Drongo": "ID",
    "Sulawesi Drongo": "ID",
    "Moluccan Flycatcher": "ID",
    "Biak Flycatcher": "ID",
    "Flores Monarch": "ID",
    "Kofiau Monarch": "ID",
    "Biak Monarch": "ID",
    "White-naped Monarch": "ID",
    "Tanimbar Monarch": "ID",
    "Pale-blue Monarch": "ID",
    "Sumatran Treepie": "ID",
    "Flores Crow": "ID",
    "Piping Crow": "ID",
    "Banggai Crow": "ID",
    "Violet Crow": "ID",
    "Long-billed Crow": "ID",
    "Brown-headed Crow": "ID",
    "Halmahera Paradise-crow": "ID",
    "Obi Paradise-crow": "ID",
    "Bronze Parotia": "ID",
    "Western Parotia": "ID",
    "Vogelkop Lophorina": "ID",
    "Long-tailed Paradigalla": "ID",
    "Arfak Astrapia": "ID",
    "Snow Mountain Robin": "ID",
    "Smoky Robin": "ID",
    "Bar-winged Prinia": "ID",
    "Olive-backed Tailorbird": "ID",
    "Malia": "ID",
    "Brown-cheeked Bulbul": "ID",
    "Cream-striped Bulbul": "ID",
    "Sumatran Bulbul": "ID",
    "Javan Bulbul": "ID",
    "Ruby-throated Bulbul": "ID",
    "Spot-necked Bulbul": "ID",
    "Aceh Bulbul": "ID",
    "Orange-spotted Bulbul": "ID",
    "Javan Tesia": "ID",
    "Russet-capped Tesia": "ID",
    "Pygmy Tit": "ID",
    "Sangkar White-eye": "ID",
    "Lemon-bellied White-eye": "ID",
    "Wakatobi White-eye": "ID",
    "Black-ringed White-eye": "ID",
    "Black-crowned White-eye": "ID",
    "Togian White-eye": "ID",
    "Sangihe White-eye": "ID",
    "Seram White-eye": "ID",
    "Cream-throated White-eye": "ID",
    "Morotai White-eye": "ID",
    "Biak White-eye": "ID",
    "Buru White-eye": "ID",
    "Ambon White-eye": "ID",
    "White-breasted Babbler": "ID",
    "White-bibbed Babbler": "ID",
    "Crescent-chested Babbler": "ID",
    "Sulawesi Babbler": "ID",
    "Sumatran Babbler": "ID",
    "Black-browed Babbler": "ID",
    "Javan Fulvetta": "ID",
    "Rufous-fronted Laughingthrush": "ID",
    "Sumatran Laughingthrush": "ID",
    "Spotted Crocias": "ID",
    "Javan Pied Starling": "ID",
    "Bali Myna": "ID",
    "Black-winged Myna": "ID",
    "Pale-bellied Myna": "ID",
    "Javan Myna": "ID",
    "Sulawesi Myna": "ID",
    "Helmeted Myna": "ID",
    "Long-crested Myna": "ID",
    "Bare-eyed Myna": "ID",
    "Tenggara Hill Myna": "ID",
    "Tanimbar Starling": "ID",
    "Long-tailed Starling": "ID",
    "Moluccan Starling": "ID",
    "Geomalia": "ID",
    "Fawn-breasted Thrush": "ID",
    "Sumatran Cochoa": "ID",
    "Javan Cochoa": "ID",
    "Red-and-black Thrush": "ID",
    "Slaty-backed Thrush": "ID",
    "Enggano Thrush": "ID",
    "Buru Thrush": "ID",
    "Seram Thrush": "ID",
    "Sulawesi Thrush": "ID",
    "Sumba Brown Flycatcher": "ID",
    "Indigo Flycatcher": "ID",
    "Blue-fronted Flycatcher": "ID",
    "Matinan Flycatcher": "ID",
    "Great Shortwing": "ID",
    "Sumatran Shortwing": "ID",
    "Javan Shortwing": "ID",
    "Flores Shortwing": "ID",
    "Sunda Forktail": "ID",
    "Damar Flycatcher": "ID",
    "Rufous-throated Flycatcher": "ID",
    "Cinnamon-chested Flycatcher": "ID",
    "Sumba Flycatcher": "ID",
    "Lompobattang Flycatcher": "ID",
    "Tanimbar Flycatcher": "ID",
    "Sumatran Leafbird": "ID",
    "Blue-masked Leafbird": "ID",
    "Javan Leafbird": "ID",
    "Golden-rumped Flowerpecker": "ID",
    "Yellow-sided Flowerpecker": "ID",
    "Crimson-crowned Flowerpecker": "ID",
    "Halmahera Flowerpecker": "ID",
    "Buru Flowerpecker": "ID",
    "Ashy Flowerpecker": "ID",
    "Olive-crowned Flowerpecker": "ID",
    "Sumba Flowerpecker": "ID",
    "Scarlet-headed Flowerpecker": "ID",
    "Black-fronted Flowerpecker": "ID",
    "Sumatran Flowerpecker": "ID",
    "Pink-breasted Flowerpecker": "ID",
    "Streaky-breasted Spiderhunter": "ID",
    "Apricot-breasted Sunbird": "ID",
    "Elegant Sunbird": "ID",
    "Javan Sunbird": "ID",
    "White-flanked Sunbird": "ID",
    "Javan Munia": "ID",
    "White-capped Munia": "ID",
    "Java Sparrow": "ID",
    "Madanga": "ID",
    "Malleefowl": "AU",
    "Stubble Quail": "AU",
    "Blue-billed Duck": "AU",
    "Musk Duck": "AU",
    "Pink-eared Duck": "AU",
    "Freckled Duck": "AU",
    "Cape Barren Goose": "AU",
    "Black Swan": "AU",
    "Maned Duck": "AU",
    "Hardhead": "AU",
    "Chestnut Teal": "AU",
    "Hoary-headed Grebe": "AU",
    "White-headed Pigeon": "AU",
    "Wonga Pigeon": "AU",
    "Spinifex Pigeon": "AU",
    "Squatter Pigeon": "AU",
    "Partridge Pigeon": "AU",
    "Common Bronzewing": "AU",
    "Brush Bronzewing": "AU",
    "Flock Bronzewing": "AU",
    "Crested Pigeon": "AU",
    "Diamond Dove": "AU",
    "Topknot Pigeon": "AU",
    "Tawny Frogmouth": "AU",
    "Australian Swiftlet": "AU",
    "Australian Crake": "AU",
    "Royal Penguin": "AU",
    "Yellow-billed Spoonbill": "AU",
    "Black-faced Cormorant": "AU",
    "Sooty Oystercatcher": "AU",
    "Banded Stilt": "AU",
    "Red-necked Avocet": "AU",
    "Hooded Plover": "AU",
    "Banded Lapwing": "AU",
    "Inland Dotterel": "AU",
    "Plains-wanderer": "AU",
    "Black-breasted Buttonquail": "AU",
    "Painted Buttonquail": "AU",
    "Buff-breasted Buttonquail": "AU",
    "Chestnut-backed Buttonquail": "AU",
    "Red-chested Buttonquail": "AU",
    "Little Buttonquail": "AU",
    "Pacific Gull": "AU",
    "Powerful Owl": "AU",
    "Tasmanian Boobook": "AU",
    "Black-shouldered Kite": "AU",
    "Letter-winged Kite": "AU",
    "Square-tailed Kite": "AU",
    "Little Eagle": "AU",
    "Red Goshawk": "AU",
    "Red-backed Kingfisher": "AU",
    "Laughing Kookaburra": "AU",
    "Black Falcon": "AU",
    "Cockatiel": "AU",
    "Gang-gang Cockatoo": "AU",
    "Galah": "AU",
    "Long-billed Corella": "AU",
    "Western Corella": "AU",
    "Red-rumped Parrot": "AU",
    "Greater Bluebonnet": "AU",
    "Naretha Bluebonnet": "AU",
    "Mulga Parrot": "AU",
    "Hooded Parrot": "AU",
    "Golden-shouldered Parrot": "AU",
    "Red-capped Parrot": "AU",
    "Green Rosella": "AU",
    "Crimson Rosella": "AU",
    "Northern Rosella": "AU",
    "Pale-headed Rosella": "AU",
    "Eastern Rosella": "AU",
    "Western Rosella": "AU",
    "Australian Ringneck": "AU",
    "Swift Parrot": "AU",
    "Night Parrot": "AU",
    "Bourke's Parrot": "AU",
    "Blue-winged Parrot": "AU",
    "Elegant Parrot": "AU",
    "Rock Parrot": "AU",
    "Orange-bellied Parrot": "AU",
    "Turquoise Parrot": "AU",
    "Scarlet-chested Parrot": "AU",
    "Musk Lorikeet": "AU",
    "Little Lorikeet": "AU",
    "Purple-crowned Lorikeet": "AU",
    "Varied Lorikeet": "AU",
    "Rainbow Lorikeet": "AU",
    "Red-collared Lorikeet": "AU",
    "Scaly-breasted Lorikeet": "AU",
    "Budgerigar": "AU",
    "Superb Parrot": "AU",
    "Regent Parrot": "AU",
    "Princess Parrot": "AU",
    "Rainbow Pitta": "AU",
    "Albert's Lyrebird": "AU",
    "Superb Lyrebird": "AU",
    "Rufous Scrub-bird": "AU",
    "Noisy Scrub-bird": "AU",
    "Spotted Catbird": "AU",
    "Green Catbird": "AU",
    "Tooth-billed Bowerbird": "AU",
    "Golden Bowerbird": "AU",
    "Regent Bowerbird": "AU",
    "Satin Bowerbird": "AU",
    "Spotted Bowerbird": "AU",
    "Western Bowerbird": "AU",
    "Great Bowerbird": "AU",
    "White-throated Treecreeper": "AU",
    "Red-browed Treecreeper": "AU",
    "White-browed Treecreeper": "AU",
    "Rufous Treecreeper": "AU",
    "Brown Treecreeper": "AU",
    "Black-tailed Treecreeper": "AU",
    "White-throated Grasswren": "AU",
    "Carpentarian Grasswren": "AU",
    "Pilbara Grasswren": "AU",
    "Sandhill Grasswren": "AU",
    "Striated Grasswren": "AU",
    "Short-tailed Grasswren": "AU",
    "Black Grasswren": "AU",
    "Eyrean Grasswren": "AU",
    "Kalkadoon Grasswren": "AU",
    "Dusky Grasswren": "AU",
    "Western Grasswren": "AU",
    "Thick-billed Grasswren": "AU",
    "Eastern Bristlebird": "AU",
    "Western Bristlebird": "AU",
    "Rufous Bristlebird": "AU",
    "Banded Honeyeater": "AU",
    "White-streaked Honeyeater": "AU",
    "Crescent Honeyeater": "AU",
    "White-cheeked Honeyeater": "AU",
    "New Holland Honeyeater": "AU",
    "Gilbert's Honeyeater": "AU",
    "White-naped Honeyeater": "AU",
    "Black-headed Honeyeater": "AU",
    "Strong-billed Honeyeater": "AU",
    "Black-chinned Honeyeater": "AU",
    "Brown-headed Honeyeater": "AU",
    "White-eared Honeyeater": "AU",
    "Yellow-throated Honeyeater": "AU",
    "Macleay's Honeyeater": "AU",
    "Striped Honeyeater": "AU",
    "Painted Honeyeater": "AU",
    "Silver-crowned Friarbird": "AU",
    "Black Honeyeater": "AU",
    "Scarlet Myzomela": "AU",
    "Western Spinebill": "AU",
    "Eastern Spinebill": "AU",
    "Pied Honeyeater": "AU",
    "Tawny-crowned Honeyeater": "AU",
    "Bar-breasted Honeyeater": "AU",
    "Rufous-throated Honeyeater": "AU",
    "Gibberbird": "AU",
    "Yellow Chat": "AU",
    "Crimson Chat": "AU",
    "White-fronted Chat": "AU",
    "Orange Chat": "AU",
    "Yellow-spotted Honeyeater": "AU",
    "Lewin's Honeyeater": "AU",
    "Kimberley Honeyeater": "AU",
    "White-lined Honeyeater": "AU",
    "White-gaped Honeyeater": "AU",
    "Yellow Honeyeater": "AU",
    "Bridled Honeyeater": "AU",
    "Eungella Honeyeater": "AU",
    "Spiny-cheeked Honeyeater": "AU",
    "Western Wattlebird": "AU",
    "Little Wattlebird": "AU",
    "Regent Honeyeater": "AU",
    "Red Wattlebird": "AU",
    "Yellow Wattlebird": "AU",
    "Singing Honeyeater": "AU",
    "Mangrove Honeyeater": "AU",
    "White-plumed Honeyeater": "AU",
    "Yellow-plumed Honeyeater": "AU",
    "Fuscous Honeyeater": "AU",
    "White-fronted Honeyeater": "AU",
    "Yellow-faced Honeyeater": "AU",
    "Purple-gaped Honeyeater": "AU",
    "Yellow-tufted Honeyeater": "AU",
    "Bell Miner": "AU",
    "Noisy Miner": "AU",
    "Black-eared Miner": "AU",
    "Yellow-throated Miner": "AU",
    "Spotted Pardalote": "AU",
    "Forty-spotted Pardalote": "AU",
    "Red-browed Pardalote": "AU",
    "Striated Pardalote": "AU",
    "Fernwren": "AU",
    "Brown Gerygone": "AU",
    "Dusky Gerygone": "AU",
    "Western Gerygone": "AU",
    "Weebill": "AU",
    "Pilotbird": "AU",
    "Redthroat": "AU",
    "Speckled Warbler": "AU",
    "Chestnut-rumped Heathwren": "AU",
    "Shy Heathwren": "AU",
    "Striated Fieldwren": "AU",
    "Western Fieldwren": "AU",
    "Rufous Fieldwren": "AU",
    "Rockwarbler": "AU",
    "Yellow-throated Scrubwren": "AU",
    "Atherton Scrubwren": "AU",
    "Tasmanian Scrubwren": "AU",
    "Spotted Scrubwren": "AU",
    "White-browed Scrubwren": "AU",
    "Large-billed Scrubwren": "AU",
    "Scrubtit": "AU",
    "Southern Whiteface": "AU",
    "Chestnut-breasted Whiteface": "AU",
    "Banded Whiteface": "AU",
    "Yellow-rumped Thornbill": "AU",
    "Yellow Thornbill": "AU",
    "Striated Thornbill": "AU",
    "Inland Thornbill": "AU",
    "Tasmanian Thornbill": "AU",
    "Brown Thornbill": "AU",
    "Mountain Thornbill": "AU",
    "Slaty-backed Thornbill": "AU",
    "Slender-billed Thornbill": "AU",
    "Chestnut-rumped Thornbill": "AU",
    "Buff-rumped Thornbill": "AU",
    "Western Thornbill": "AU",
    "Australian Logrunner": "AU",
    "Chowchilla": "AU",
    "Hall's Babbler": "AU",
    "White-browed Babbler": "AU",
    "Chestnut-crowned Babbler": "AU",
    "Varied Sittella": "AU",
    "Crested Bellbird": "AU",
    "Spotted Quail-thrush": "AU",
    "Chestnut Quail-thrush": "AU",
    "Copperback Quail-thrush": "AU",
    "Western Quail-thrush": "AU",
    "Chestnut-breasted Quail-thrush": "AU",
    "Nullarbor Quail-thrush": "AU",
    "Cinnamon Quail-thrush": "AU",
    "Northern Shrike-tit": "AU",
    "Western Shrike-tit": "AU",
    "Eastern Shrike-tit": "AU",
    "Olive Whistler": "AU",
    "Red-lored Whistler": "AU",
    "Gilbert's Whistler": "AU",
    "White-breasted Whistler": "AU",
    "Western Whipbird": "AU",
    "Eastern Whipbird": "AU",
    "Chiming Wedgebill": "AU",
    "Chirruping Wedgebill": "AU",
    "Ground Cuckooshrike": "AU",
    "Black Currawong": "AU",
    "Pied Currawong": "AU",
    "Pied Butcherbird": "AU",
    "Silver-backed Butcherbird": "AU",
    "Masked Woodswallow": "AU",
    "White-browed Woodswallow": "AU",
    "Dusky Woodswallow": "AU",
    "Little Woodswallow": "AU",
    "Restless Flycatcher": "AU",
    "Frill-necked Monarch": "AU",
    "Pied Monarch": "AU",
    "White-eared Monarch": "AU",
    "Little Crow": "AU",
    "Little Raven": "AU",
    "Forest Raven": "AU",
    "Australian Raven": "AU",
    "White-winged Chough": "AU",
    "Apostlebird": "AU",
    "Paradise Riflebird": "AU",
    "Victoria's Riflebird": "AU",
    "Rose Robin": "AU",
    "Pink Robin": "AU",
    "Flame Robin": "AU",
    "Scarlet Robin": "AU",
    "Red-capped Robin": "AU",
    "White-browed Robin": "AU",
    "Buff-sided Robin": "AU",
    "Eastern Yellow Robin": "AU",
    "Western Yellow Robin": "AU",
    "White-breasted Robin": "AU",
    "Pale-yellow Robin": "AU",
    "Dusky Robin": "AU",
    "Brown Songlark": "AU",
    "Rufous Songlark": "AU",
    "Spinifexbird": "AU",
    "White-backed Swallow": "AU",
    "Fairy Martin": "AU",
    "Australian Yellow White-eye": "AU",
    "Bassian Thrush": "AU",
    "Mistletoebird": "AU",
    "Beautiful Firetail": "AU",
    "Red-eared Firetail": "AU",
    "Diamond Firetail": "AU",
    "Star Finch": "AU",
    "Plum-headed Finch": "AU",
    "Masked Finch": "AU",
    "Long-tailed Finch": "AU",
    "Black-throated Finch": "AU",
    "Double-barred Finch": "AU",
    "Gouldian Finch": "AU",
    "Yellow-legged Tinamou": "BR",
    "Dwarf Tinamou": "BR",
    "White-crested Guan": "BR",
    "Chestnut-bellied Guan": "BR",
    "White-browed Guan": "BR",
    "East Brazilian Chachalaca": "BR",
    "Scaled Chachalaca": "BR",
    "Chestnut-headed Chachalaca": "BR",
    "Buff-browed Chachalaca": "BR",
    "Red-billed Curassow": "BR",
    "Alagoas Curassow": "BR",
    "Bahian Nighthawk": "BR",
    "Pygmy Nightjar": "BR",
    "Saw-billed Hermit": "BR",
    "Hook-billed Hermit": "BR",
    "Broad-tipped Hermit": "BR",
    "Dusky-throated Hermit": "BR",
    "Tapajos Hermit": "BR",
    "Minute Hermit": "BR",
    "Hyacinth Visorbearer": "BR",
    "Hooded Visorbearer": "BR",
    "Frilled Coquette": "BR",
    "Festive Coquette": "BR",
    "Brazilian Ruby": "BR",
    "Green-crowned Plovercrest": "BR",
    "Sombre Hummingbird": "BR",
    "Long-tailed Woodnymph": "BR",
    "Stripe-breasted Starthroat": "BR",
    "White-collared Kite": "BR",
    "White-necked Hawk": "BR",
    "Three-toed Jacamar": "BR",
    "Chestnut-headed Nunlet": "BR",
    "Brown-chested Barbet": "BR",
    "Spotted Piculet": "BR",
    "Varzea Piculet": "BR",
    "Ochraceous Piculet": "BR",
    "Kaempfer's Woodpecker": "BR",
    "Ochre-backed Woodpecker": "BR",
    "Yellow-eared Woodpecker": "BR",
    "Brown-backed Parrotlet": "BR",
    "Golden-tailed Parrotlet": "BR",
    "Plain Parakeet": "BR",
    "Blue-bellied Parrot": "BR",
    "Bald Parrot": "BR",
    "Vulturine Parrot": "BR",
    "Red-spectacled Amazon": "BR",
    "Diademed Amazon": "BR",
    "Red-browed Amazon": "BR",
    "Red-tailed Amazon": "BR",
    "Ochre-marked Parakeet": "BR",
    "Pearly Parakeet": "BR",
    "Santarem Parakeet": "BR",
    "Bonaparte's Parakeet": "BR",
    "Cactus Parakeet": "BR",
    "Jandaya Parakeet": "BR",
    "Golden-capped Parakeet": "BR",
    "Spix's Macaw": "BR",
    "Golden Parakeet": "BR",
    "Rondonia Bushbird": "BR",
    "Narrow-billed Antwren": "BR",
    "Black-hooded Antwren": "BR",
    "Serra Antwren": "BR",
    "Sincora Antwren": "BR",
    "Marsh Antwren": "BR",
    "Klages's Antwren": "BR",
    "Salvadori's Antwren": "BR",
    "Band-tailed Antwren": "BR",
    "Rio de Janeiro Antwren": "BR",
    "Unicolored Antwren": "BR",
    "Alagoas Antwren": "BR",
    "Orange-bellied Antwren": "BR",
    "Star-throated Antwren": "BR",
    "Spot-breasted Antvireo": "BR",
    "Rufous-backed Antvireo": "BR",
    "Plumbeous Antvireo": "BR",
    "Caatinga Antwren": "BR",
    "Bahia Antwren": "BR",
    "Predicted Antwren": "BR",
    "Aripuana Antwren": "BR",
    "Pectoral Antwren": "BR",
    "Silvery-cheeked Antshrike": "BR",
    "Glossy Antshrike": "BR",
    "Rio de Janeiro Antbird": "BR",
    "Bananal Antbird": "BR",
    "Ferruginous Antbird": "BR",
    "Rufous-tailed Antbird": "BR",
    "Ochre-rumped Antbird": "BR",
    "Scaled Antbird": "BR",
    "Xingu Scale-backed Antbird": "BR",
    "Pale-faced Bare-eye": "BR",
    "Bare-eyed Antbird": "BR",
    "Harlequin Antbird": "BR",
    "White-breasted Antbird": "BR",
    "Scalloped Antbird": "BR",
    "White-bibbed Antbird": "BR",
    "Squamate Antbird": "BR",
    "Rufous-faced Antbird": "BR",
    "Fringe-backed Fire-eye": "BR",
    "Slender Antbird": "BR",
    "Black-breasted Gnateater": "BR",
    "Black-cheeked Gnateater": "BR",
    "Ceara Gnateater": "BR",
    "Hooded Gnateater": "BR",
    "Black-bellied Gnateater": "BR",
    "Snethlage's Antpitta": "BR",
    "Alta Floresta Antpitta": "BR",
    "White-browed Antpitta": "BR",
    "Tapajos Antpitta": "BR",
    "Slaty Bristlefront": "BR",
    "Stresemann's Bristlefront": "BR",
    "White-breasted Tapaculo": "BR",
    "Bahia Tapaculo": "BR",
    "Boa Nova Tapaculo": "BR",
    "Mouse-colored Tapaculo": "BR",
    "Rock Tapaculo": "BR",
    "Diamantina Tapaculo": "BR",
    "Marsh Tapaculo": "BR",
    "Brasilia Tapaculo": "BR",
    "Hoffmanns's Woodcreeper": "BR",
    "Moustached Woodcreeper": "BR",
    "Ceara Woodcreeper": "BR",
    "Spix's Woodcreeper": "BR",
    "Tapajos Scythebill": "BR",
    "Xingu Scythebill": "BR",
    "Scaled Woodcreeper": "BR",
    "Wing-banded Hornero": "BR",
    "Long-tailed Cinclodes": "BR",
    "White-collared Foliage-gleaner": "BR",
    "Great Xenops": "BR",
    "Para Foliage-gleaner": "BR",
    "Pernambuco Foliage-gleaner": "BR",
    "Orange-eyed Thornbird": "BR",
    "Cipo Canastero": "BR",
    "Itatiaia Spinetail": "BR",
    "Pink-legged Graveteiro": "BR",
    "Striated Softtail": "BR",
    "Scaled Spinetail": "BR",
    "Pallid Spinetail": "BR",
    "Caatinga Cacholote": "BR",
    "Araguaia Spinetail": "BR",
    "Red-shouldered Spinetail": "BR",
    "Bahia Spinetail": "BR",
    "Pinto's Spinetail": "BR",
    "Kinglet Manakin": "BR",
    "Golden-crowned Manakin": "BR",
    "Opal-crowned Manakin": "BR",
    "Pin-tailed Manakin": "BR",
    "Araripe Manakin": "BR",
    "Hooded Berryeater": "BR",
    "Black-headed Berryeater": "BR",
    "Black-and-gold Cotinga": "BR",
    "Cinnamon-vented Piha": "BR",
    "Banded Cotinga": "BR",
    "White-tailed Cotinga": "BR",
    "White-winged Cotinga": "BR",
    "Atlantic Royal Flycatcher": "BR",
    "Buff-throated Purpletuft": "BR",
    "White-tailed Tityra": "BR",
    "Kinglet Calyptura": "BR",
    "Bahia Tyrannulet": "BR",
    "Restinga Tyrannulet": "BR",
    "Alagoas Tyrannulet": "BR",
    "Minas Gerais Tyrannulet": "BR",
    "Oustalet's Tyrannulet": "BR",
    "Chico's Tyrannulet": "BR",
    "Noronha Elaenia": "BR",
    "Ash-throated Casiornis": "BR",
    "Noronha Vireo": "BR",
    "White-naped Jay": "BR",
    "Inambari Gnatcatcher": "BR",
    "Long-billed Wren": "BR",
    "Rufous-brown Solitaire": "BR",
    "Yellow-faced Siskin": "BR",
    "Half-collared Sparrow": "BR",
    "Sao Francisco Sparrow": "BR",
    "Campo Troupial": "BR",
    "Forbes's Blackbird": "BR",
    "Pale Baywing": "BR",
    "White-striped Warbler": "BR",
    "Olive-green Tanager": "BR",
    "Rose-bellied Chat": "BR",
    "Brown Tanager": "BR",
    "Cherry-throated Tanager": "BR",
    "Scarlet-throated Tanager": "BR",
    "Rufous-headed Tanager": "BR",
    "Black-legged Dacnis": "BR",
    "Cone-billed Tanager": "BR",
    "Brazilian Tanager": "BR",
    "Dubois's Seedeater": "BR",
    "Tropeiro Seedeater": "BR",
    "White-throated Seedeater": "BR",
    "Black-bellied Seedeater": "BR",
    "Cinnamon Tanager": "BR",
    "Red-cowled Cardinal": "BR",
    "Crimson-fronted Cardinal": "BR",
    "Azure-shouldered Tanager": "BR",
    "Golden-chevroned Tanager": "BR",
    "Black-backed Tanager": "BR",
    "Seven-colored Tanager": "BR",
    "Brassy-breasted Tanager": "BR",
    "Gilt-edged Tanager": "BR",
    "White-bellied Tanager": "BR",
    "Philippine Duck": "PH",
    "Luzon Bleeding-heart": "PH",
    "Mindanao Bleeding-heart": "PH",
    "Mindoro Bleeding-heart": "PH",
    "Negros Bleeding-heart": "PH",
    "Sulu Bleeding-heart": "PH",
    "Philippine Frogmouth": "PH",
    "Philippine Nightjar": "PH",
    "Philippine Spinetail": "PH",
    "Pygmy Swiftlet": "PH",
    "Ridgetop Swiftlet": "PH",
    "Whitehead's Swiftlet": "PH",
    "Ameline Swiftlet": "PH",
    "Philippine Swiftlet": "PH",
    "Rufous Coucal": "PH",
    "Black-faced Coucal": "PH",
    "Black-hooded Coucal": "PH",
    "Philippine Coucal": "PH",
    "Red-crested Malkoha": "PH",
    "Scale-feathered Malkoha": "PH",
    "Calayan Rail": "PH",
    "Philippine Swamphen": "PH",
    "Bukidnon Woodcock": "PH",
    "Spotted Buttonquail": "PH",
    "Luzon Buttonquail": "PH",
    "Chocolate Boobook": "PH",
    "Luzon Boobook": "PH",
    "Mindanao Boobook": "PH",
    "Camiguin Boobook": "PH",
    "Sulu Boobook": "PH",
    "Cebu Boobook": "PH",
    "Romblon Boobook": "PH",
    "Mindoro Boobook": "PH",
    "Philippine Honey-buzzard": "PH",
    "Philippine Eagle": "PH",
    "Philippine Trogon": "PH",
    "Sulu Hornbill": "PH",
    "Palawan Hornbill": "PH",
    "Writhed Hornbill": "PH",
    "Visayan Hornbill": "PH",
    "Samar Hornbill": "PH",
    "Mindanao Hornbill": "PH",
    "Mindoro Hornbill": "PH",
    "Luzon Hornbill": "PH",
    "Rufous-crowned Bee-eater": "PH",
    "White-throated Kingfisher": "PH",
    "Spotted Kingfisher": "PH",
    "Blue-capped Kingfisher": "PH",
    "Rufous-lored Kingfisher": "PH",
    "Red-headed Flameback": "PH",
    "Luzon Flameback": "PH",
    "Buff-spotted Flameback": "PH",
    "Yellow-faced Flameback": "PH",
    "Spot-throated Flameback": "PH",
    "Philippine Pygmy Woodpecker": "PH",
    "Sulu Pygmy Woodpecker": "PH",
    "Philippine Falconet": "PH",
    "Philippine Cockatoo": "PH",
    "Mindanao Lorikeet": "PH",
    "Guaiabero": "PH",
    "Mindanao Racquet-tail": "PH",
    "Blue-headed Racquet-tail": "PH",
    "Mindoro Racquet-tail": "PH",
    "Green Racquet-tail": "PH",
    "Blue-crowned Racquet-tail": "PH",
    "Philippine Pitta": "PH",
    "Whiskered Pitta": "PH",
    "Azure-breasted Pitta": "PH",
    "Philippine Oriole": "PH",
    "White-lored Oriole": "PH",
    "Isabela Oriole": "PH",
    "Yellow-bellied Whistler": "PH",
    "Green-backed Whistler": "PH",
    "Visayan Cuckooshrike": "PH",
    "McGregor's Cuckooshrike": "PH",
    "Black-bibbed Cicadabird": "PH",
    "Black-and-cinnamon Fantail": "PH",
    "Blue-headed Fantail": "PH",
    "Tablas Fantail": "PH",
    "Visayan Fantail": "PH",
    "Balicassiao": "PH",
    "Short-tailed Drongo": "PH",
    "Tablas Drongo": "PH",
    "Short-crested Monarch": "PH",
    "Celestial Monarch": "PH",
    "Mountain Shrike": "PH",
    "Philippine Jungle Crow": "PH",
    "Elegant Tit": "PH",
    "Palawan Tit": "PH",
    "White-fronted Tit": "PH",
    "Rufous-fronted Tailorbird": "PH",
    "Green-backed Tailorbird": "PH",
    "Yellow-breasted Tailorbird": "PH",
    "White-eared Tailorbird": "PH",
    "Sulphur-bellied Bulbul": "PH",
    "Zamboanga Bulbul": "PH",
    "Yellowish Bulbul": "PH",
    "Camiguin Bulbul": "PH",
    "Streak-breasted Bulbul": "PH",
    "Philippine Bulbul": "PH",
    "Mindoro Bulbul": "PH",
    "Visayan Bulbul": "PH",
    "Yellow-wattled Bulbul": "PH",
    "Ashy-fronted Bulbul": "PH",
    "Rufous-headed Tailorbird": "PH",
    "Chestnut-faced Babbler": "PH",
    "Golden-crowned Babbler": "PH",
    "Rusty-crowned Babbler": "PH",
    "Flame-templed Babbler": "PH",
    "Yellowish White-eye": "PH",
    "Ashy-headed Babbler": "PH",
    "Sulphur-billed Nuthatch": "PH",
    "Visayan Rhabdornis": "PH",
    "Stripe-breasted Rhabdornis": "PH",
    "Apo Myna": "PH",
    "Coleto": "PH",
    "Ashy Thrush": "PH",
    "White-browed Shama": "PH",
    "Visayan Shama": "PH",
    "White-vented Shama": "PH",
    "Black Shama": "PH",
    "Ashy-breasted Flycatcher": "PH",
    "Philippine Shortwing": "PH",
    "Little Slaty Flycatcher": "PH",
    "Cryptic Flycatcher": "PH",
    "Furtive Flycatcher": "PH",
    "Palawan Flycatcher": "PH",
    "Palawan Fairy-bluebird": "PH",
    "Philippine Fairy-bluebird": "PH",
    "Yellow-throated Leafbird": "PH",
    "Philippine Leafbird": "PH",
    "Olive-backed Flowerpecker": "PH",
    "Palawan Flowerpecker": "PH",
    "Whiskered Flowerpecker": "PH",
    "Yellow-crowned Flowerpecker": "PH",
    "Flame-crowned Flowerpecker": "PH",
    "Red-keeled Flowerpecker": "PH",
    "Black-belted Flowerpecker": "PH",
    "Scarlet-collared Flowerpecker": "PH",
    "Cebu Flowerpecker": "PH",
    "Buzzing Flowerpecker": "PH",
    "Olive-capped Flowerpecker": "PH",
    "Pygmy Flowerpecker": "PH",
    "Fire-throated Flowerpecker": "PH",
    "Orange-tufted Spiderhunter": "PH",
    "Naked-faced Spiderhunter": "PH",
    "Lovely Sunbird": "PH",
    "Magnificent Sunbird": "PH",
    "Metallic-winged Sunbird": "PH",
    "Flaming Sunbird": "PH",
    "Maroon-naped Sunbird": "PH",
    "Handsome Sunbird": "PH",
    "Lina's Sunbird": "PH",
    "Apo Sunbird": "PH",
    "Tboli Sunbird": "PH",
    "Green-faced Parrotfinch": "PH",
    "Red-eared Parrotfinch": "PH",
    "Cinnamon Ibon": "PH",
    "White-cheeked Bullfinch": "PH",
    "Mindanao Serin": "PH",
    "White-winged Guan": "PE",
    "Sira Curassow": "PE",
    "Junin Grebe": "PE",
    "Koepcke's Hermit": "PE",
    "Peruvian Piedtail": "PE",
    "Bronze-tailed Comet": "PE",
    "Black-breasted Hillstar": "PE",
    "Coppery Metaltail": "PE",
    "Fire-throated Metaltail": "PE",
    "Black Metaltail": "PE",
    "Marvelous Spatuletail": "PE",
    "White-tufted Sunbeam": "PE",
    "Purple-backed Sunbeam": "PE",
    "Rufous-webbed Brilliant": "PE",
    "Spot-throated Hummingbird": "PE",
    "Green-and-white Hummingbird": "PE",
    "Long-whiskered Owlet": "PE",
    "Yellow-browed Toucanet": "PE",
    "Scarlet-banded Barbet": "PE",
    "Sira Barbet": "PE",
    "Speckle-chested Piculet": "PE",
    "Black-necked Woodpecker": "PE",
    "Yellow-faced Parrotlet": "PE",
    "Creamy-bellied Antwren": "PE",
    "Ash-throated Antwren": "PE",
    "Marañon Antshrike": "PE",
    "White-masked Antbird": "PE",
    "Cordillera Azul Antbird": "PE",
    "Allpahuayo Antbird": "PE",
    "Pale-billed Antpitta": "PE",
    "Rusty-tinged Antpitta": "PE",
    "Bay Antpitta": "PE",
    "Red-and-white Antpitta": "PE",
    "Chestnut Antpitta": "PE",
    "Ochre-fronted Antpitta": "PE",
    "Junin Tapaculo": "PE",
    "Unicolored Tapaculo": "PE",
    "Large-footed Tapaculo": "PE",
    "Rufous-vented Tapaculo": "PE",
    "Neblina Tapaculo": "PE",
    "Ancash Tapaculo": "PE",
    "Tschudi's Tapaculo": "PE",
    "Vilcabamba Tapaculo": "PE",
    "Coastal Miner": "PE",
    "Thick-billed Miner": "PE",
    "Dark-winged Miner": "PE",
    "Striated Earthcreeper": "PE",
    "White-bellied Cinclodes": "PE",
    "Surf Cinclodes": "PE",
    "Chestnut-backed Thornbird": "PE",
    "Junin Canastero": "PE",
    "Rusty-fronted Canastero": "PE",
    "Eye-ringed Thistletail": "PE",
    "Vilcabamba Thistletail": "PE",
    "Ayacucho Thistletail": "PE",
    "Marcapata Spinetail": "PE",
    "Vilcabamba Spinetail": "PE",
    "Russet-mantled Softtail": "PE",
    "Creamy-crested Spinetail": "PE",
    "Cactus Canastero": "PE",
    "Great Spinetail": "PE",
    "Russet-bellied Spinetail": "PE",
    "Chinchipe Spinetail": "PE",
    "Apurimac Spinetail": "PE",
    "Painted Manakin": "PE",
    "Cerulean-capped Manakin": "PE",
    "Masked Fruiteater": "PE",
    "White-cheeked Cotinga": "PE",
    "Peruvian Plantcutter": "PE",
    "Bay-vented Cotinga": "PE",
    "Inca Flycatcher": "PE",
    "Mishana Tyrannulet": "PE",
    "Peruvian Tyrannulet": "PE",
    "Rufous Flycatcher": "PE",
    "Marañon Gnatcatcher": "PE",
    "Iquitos Gnatcatcher": "PE",
    "Inca Wren": "PE",
    "Peruvian Wren": "PE",
    "Selva Cacique": "PE",
    "Cinereous Finch": "PE",
    "Rufous-browed Hemispingus": "PE",
    "Parodi's Hemispingus": "PE",
    "Brown-flanked Tanager": "PE",
    "Pardusco": "PE",
    "Tit-like Dacnis": "PE",
    "Yellow-scarfed Tanager": "PE",
    "Sira Tanager": "PE",
    "New Britain Bronzewing": "PG",
    "Pied Coucal": "PG",
    "Violaceous Coucal": "PG",
    "New Britain Rail": "PG",
    "Manus Boobook": "PG",
    "New Britain Boobook": "PG",
    "Bismarck Boobook": "PG",
    "Black Honey-buzzard": "PG",
    "New Britain Goshawk": "PG",
    "New Britain Sparrowhawk": "PG",
    "Bismarck Kingfisher": "PG",
    "New Britain Kingfisher": "PG",
    "Torresian Kingfisher": "PG",
    "Colonist Kingfisher": "PG",
    "Blue-eyed Cockatoo": "PG",
    "Red-chinned Lorikeet": "PG",
    "Purple-bellied Lory": "PG",
    "White-naped Lory": "PG",
    "Louisiade Pitta": "PG",
    "Superb Pitta": "PG",
    "Streaked Bowerbird": "PG",
    "Fire-maned Bowerbird": "PG",
    "New Britain Friarbird": "PG",
    "New Ireland Friarbird": "PG",
    "White-naped Friarbird": "PG",
    "Bismarck Honeyeater": "PG",
    "White-chinned Myzomela": "PG",
    "Ashy Myzomela": "PG",
    "Reddish Myzomela": "PG",
    "New Ireland Myzomela": "PG",
    "Sclater's Myzomela": "PG",
    "Bismarck Black Myzomela": "PG",
    "Black-bellied Myzomela": "PG",
    "Long-billed Myzomela": "PG",
    "Rufous-backed Honeyeater": "PG",
    "Bougainville Honeyeater": "PG",
    "Spangled Honeyeater": "PG",
    "Elegant Honeyeater": "PG",
    "Tagula Honeyeater": "PG",
    "Long-bearded Honeyeater": "PG",
    "Dimorphic Jewel-babbler": "PG",
    "Bougainville Hooded Whistler": "PG",
    "Brown-backed Whistler": "PG",
    "White-bellied Whistler": "PG",
    "Bismarck Whistler": "PG",
    "Louisiade Whistler": "PG",
    "Rossel Cicadabird": "PG",
    "Mussau Triller": "PG",
    "Tagula Butcherbird": "PG",
    "Bismarck Fantail": "PG",
    "Mussau Fantail": "PG",
    "Manus Fantail": "PG",
    "Bougainville Fantail": "PG",
    "Ribbon-tailed Drongo": "PG",
    "Mussau Flycatcher": "PG",
    "Velvet Flycatcher": "PG",
    "Manus Monarch": "PG",
    "Bougainville Crow": "PG",
    "Bismarck Crow": "PG",
    "Curl-crested Manucode": "PG",
    "Wahnes's Parotia": "PG",
    "Lawes's Parotia": "PG",
    "Eastern Parotia": "PG",
    "Lesser Lophorina": "PG",
    "Growling Riflebird": "PG",
    "Huon Astrapia": "PG",
    "Stephanie's Astrapia": "PG",
    "Ribbon-tailed Astrapia": "PG",
    "Spotted Berrypecker": "PG",
    "Bougainville Thicketbird": "PG",
    "Rusty Thicketbird": "PG",
    "Tagula White-eye": "PG",
    "Louisiade White-eye": "PG",
    "Bougainville White-eye": "PG",
    "New Britain Thrush": "PG",
    "Bougainville Thrush": "PG",
    "Red-banded Flowerpecker": "PG",
    "Louisiade Flowerpecker": "PG",
    "Rufous-bellied Chachalaca": "MX",
    "West Mexican Chachalaca": "MX",
    "Banded Quail": "MX",
    "Elegant Quail": "MX",
    "Socorro Dove": "MX",
    "Eared Poorwill": "MX",
    "Tawny-collared Nightjar": "MX",
    "White-fronted Swift": "MX",
    "White-naped Swift": "MX",
    "Mexican Hermit": "MX",
    "Short-crested Coquette": "MX",
    "Golden-crowned Emerald": "MX",
    "Cozumel Emerald": "MX",
    "Dusky Hummingbird": "MX",
    "Turquoise-crowned Hummingbird": "MX",
    "Tres Marias Hummingbird": "MX",
    "White-tailed Hummingbird": "MX",
    "Mexican Woodnymph": "MX",
    "Xantus's Hummingbird": "MX",
    "Mexican Sheartail": "MX",
    "Beautiful Hummingbird": "MX",
    "Bumblebee Hummingbird": "MX",
    "Townsend's Shearwater": "MX",
    "Cinereous Owl": "MX",
    "Citreoline Trogon": "MX",
    "Imperial Woodpecker": "MX",
    "Golden-cheeked Woodpecker": "MX",
    "Strickland's Woodpecker": "MX",
    "Lilac-crowned Amazon": "MX",
    "Red-crowned Amazon": "MX",
    "Mexican Parrotlet": "MX",
    "Thick-billed Parrot": "MX",
    "Maroon-fronted Parrot": "MX",
    "Green Parakeet": "MX",
    "Socorro Parakeet": "MX",
    "White-striped Woodcreeper": "MX",
    "Flammulated Flycatcher": "MX",
    "Pileated Flycatcher": "MX",
    "Slaty Vireo": "MX",
    "Dwarf Vireo": "MX",
    "Cozumel Vireo": "MX",
    "Sinaloa Crow": "MX",
    "White-throated Jay": "MX",
    "Dwarf Jay": "MX",
    "Tufted Jay": "MX",
    "San Blas Jay": "MX",
    "Purplish-backed Jay": "MX",
    "Yucatan Gnatcatcher": "MX",
    "Sumichrast's Wren": "MX",
    "Nava's Wren": "MX",
    "Clarion Wren": "MX",
    "Cozumel Wren": "MX",
    "Socorro Wren": "MX",
    "Spotted Wren": "MX",
    "Yucatan Wren": "MX",
    "Boucard's Wren": "MX",
    "Happy Wren": "MX",
    "Sinaloa Wren": "MX",
    "Blue Mockingbird": "MX",
    "Socorro Mockingbird": "MX",
    "Ocellated Thrasher": "MX",
    "Cozumel Thrasher": "MX",
    "Aztec Thrush": "MX",
    "Worthen's Sparrow": "MX",
    "Cinnamon-tailed Sparrow": "MX",
    "Black-chested Sparrow": "MX",
    "Bridled Sparrow": "MX",
    "Collared Towhee": "MX",
    "White-throated Towhee": "MX",
    "Oaxaca Sparrow": "MX",
    "Guadalupe Junco": "MX",
    "Baird's Junco": "MX",
    "Striped Sparrow": "MX",
    "Sierra Madre Sparrow": "MX",
    "Black-backed Oriole": "MX",
    "Black-polled Yellowthroat": "MX",
    "Belding's Yellowthroat": "MX",
    "Altamira Yellowthroat": "MX",
    "Hooded Yellowthroat": "MX",
    "Red Warbler": "MX",
    "Rose-bellied Bunting": "MX",
    "Orange-breasted Bunting": "MX",
    "Red-headed Tanager": "MX",
    "Crimson-collared Grosbeak": "MX",
    "Cinnamon-rumped Seedeater": "MX",
    "Madagascar Partridge": "MG",
    "Madagascar Pochard": "MG",
    "Meller's Duck": "MG",
    "Madagascar Grebe": "MG",
    "White-breasted Mesite": "MG",
    "Brown Mesite": "MG",
    "Subdesert Mesite": "MG",
    "Madagascar Sandgrouse": "MG",
    "Collared Nightjar": "MG",
    "Giant Coua": "MG",
    "Coquerel's Coua": "MG",
    "Red-breasted Coua": "MG",
    "Red-fronted Coua": "MG",
    "Running Coua": "MG",
    "Red-capped Coua": "MG",
    "Olive-capped Coua": "MG",
    "Crested Coua": "MG",
    "Verreaux's Coua": "MG",
    "Blue Coua": "MG",
    "Madagascar Flufftail": "MG",
    "Slender-billed Flufftail": "MG",
    "Madagascar Rail": "MG",
    "Sakalava Rail": "MG",
    "Madagascar Jacana": "MG",
    "Madagascar Snipe": "MG",
    "White-browed Owl": "MG",
    "Madagascar Sparrowhawk": "MG",
    "Henst's Goshawk": "MG",
    "Madagascar Buzzard": "MG",
    "Madagascar Hoopoe": "MG",
    "Banded Kestrel": "MG",
    "Velvet Asity": "MG",
    "Schlegel's Asity": "MG",
    "Madagascar Cuckooshrike": "MG",
    "Archbold's Newtonia": "MG",
    "Common Newtonia": "MG",
    "Red-tailed Newtonia": "MG",
    "Dark Newtonia": "MG",
    "Tylas Vanga": "MG",
    "Red-tailed Vanga": "MG",
    "Red-shouldered Vanga": "MG",
    "Chabert Vanga": "MG",
    "Madagascar Blue Vanga": "MG",
    "Crossley's Vanga": "MG",
    "Hook-billed Vanga": "MG",
    "Rufous Vanga": "MG",
    "Helmet Vanga": "MG",
    "Pollen's Vanga": "MG",
    "Lafresnaye's Vanga": "MG",
    "Van Dam's Vanga": "MG",
    "Bernier's Vanga": "MG",
    "Sickle-billed Vanga": "MG",
    "White-headed Vanga": "MG",
    "Madagascar Lark": "MG",
    "Green Jery": "MG",
    "Common Jery": "MG",
    "Stripe-throated Jery": "MG",
    "White-throated Oxylabes": "MG",
    "Thamnornis": "MG",
    "Spectacled Tetraka": "MG",
    "Appert's Tetraka": "MG",
    "Dusky Tetraka": "MG",
    "Madagascar Yellowbrow": "MG",
    "Cryptic Warbler": "MG",
    "Rand's Warbler": "MG",
    "Madagascar Starling": "MG",
    "Red Fody": "MG",
    "Forest Fody": "MG",
    "Nelicourvi Weaver": "MG",
    "Sakalava Weaver": "MG",
    "Madagascar Munia": "MG",
    "Madagascar Wagtail": "MG",
    "Cauca Guan": "CO",
    "Chestnut-winged Chachalaca": "CO",
    "Colombian Chachalaca": "CO",
    "Blue-billed Curassow": "CO",
    "Tolima Dove": "CO",
    "Black-backed Thornbill": "CO",
    "Blue-bearded Helmetcrest": "CO",
    "Green-bearded Helmetcrest": "CO",
    "Buffy Helmetcrest": "CO",
    "Gorgeted Puffleg": "CO",
    "Colorful Puffleg": "CO",
    "Black Inca": "CO",
    "White-tailed Starfrontlet": "CO",
    "Golden-bellied Starfrontlet": "CO",
    "Chiribiquete Emerald": "CO",
    "Santa Marta Blossomcrown": "CO",
    "Tolima Blossomcrown": "CO",
    "Santa Marta Sabrewing": "CO",
    "Chestnut-bellied Hummingbird": "CO",
    "Indigo-capped Hummingbird": "CO",
    "Sapphire-bellied Hummingbird": "CO",
    "Santa Marta Woodstar": "CO",
    "Bogota Rail": "CO",
    "Sooty-capped Puffbird": "CO",
    "White-mantled Barbet": "CO",
    "Beautiful Woodpecker": "CO",
    "Rufous-fronted Parakeet": "CO",
    "Indigo-winged Parrot": "CO",
    "Turquoise-winged Parrotlet": "CO",
    "Santa Marta Parakeet": "CO",
    "Brown-breasted Parakeet": "CO",
    "Yellow-eared Parrot": "CO",
    "Parker's Antbird": "CO",
    "Santa Marta Antbird": "CO",
    "East Andean Antbird": "CO",
    "Santa Marta Antpitta": "CO",
    "Cundinamarca Antpitta": "CO",
    "Urrao Antpitta": "CO",
    "Brown-banded Antpitta": "CO",
    "Santa Marta Tapaculo": "CO",
    "Magdalena Tapaculo": "CO",
    "Stiles's Tapaculo": "CO",
    "Tatama Tapaculo": "CO",
    "Brown-rumped Tapaculo": "CO",
    "Paramillo Tapaculo": "CO",
    "Santa Marta Foliage-gleaner": "CO",
    "Rusty-headed Spinetail": "CO",
    "Silvery-throated Spinetail": "CO",
    "Chestnut-capped Piha": "CO",
    "Apical Flycatcher": "CO",
    "San Andres Vireo": "CO",
    "Santa Marta Wren": "CO",
    "Apolinar's Wren": "CO",
    "Antioquia Wren": "CO",
    "Niceforo's Wren": "CO",
    "Velvet-fronted Euphonia": "CO",
    "Baudo Oropendola": "CO",
    "Red-bellied Grackle": "CO",
    "Mountain Grackle": "CO",
    "Santa Marta Warbler": "CO",
    "White-lored Warbler": "CO",
    "Turquoise Dacnis": "CO",
    "Flame-rumped Tanager": "CO",
    "Chestnut-bellied Flowerpiercer": "CO",
    "Multicolored Tanager": "CO",
    "Gold-ringed Tanager": "CO",
    "Black-and-gold Tanager": "CO",
    "Red Spurfowl": "IN",
    "Painted Spurfowl": "IN",
    "Himalayan Quail": "IN",
    "Andaman Nightjar": "IN",
    "Andaman Crake": "IN",
    "Jerdon's Courser": "IN",
    "Hume's Boobook": "IN",
    "Andaman Boobook": "IN",
    "Forest Owlet": "IN",
    "Nicobar Sparrowhawk": "IN",
    "Narcondam Hornbill": "IN",
    "Malabar Barbet": "IN",
    "White-cheeked Barbet": "IN",
    "Andaman Woodpecker": "IN",
    "Nicobar Parakeet": "IN",
    "Malabar Parakeet": "IN",
    "White-bellied Minivet": "IN",
    "Andaman Cuckooshrike": "IN",
    "Malabar Woodshrike": "IN",
    "White-bellied Treepie": "IN",
    "Andaman Treepie": "IN",
    "White-naped Tit": "IN",
    "Malabar Lark": "IN",
    "Broad-tailed Grassbird": "IN",
    "Nicobar Bulbul": "IN",
    "Andaman Bulbul": "IN",
    "Flame-throated Bulbul": "IN",
    "Yellow-throated Bulbul": "IN",
    "Black-breasted Parrotbill": "IN",
    "Rufous Babbler": "IN",
    "Wayanad Laughingthrush": "IN",
    "Palani Laughingthrush": "IN",
    "Ashambu Laughingthrush": "IN",
    "Banasura Laughingthrush": "IN",
    "Nilgiri Laughingthrush": "IN",
    "Bugun Liocichla": "IN",
    "Indian Spotted Creeper": "IN",
    "Malabar Starling": "IN",
    "White-headed Starling": "IN",
    "Nilgiri Thrush": "IN",
    "Andaman Shama": "IN",
    "Nilgiri Flycatcher": "IN",
    "Nilgiri Sholakili": "IN",
    "White-bellied Sholakili": "IN",
    "Black-and-orange Flycatcher": "IN",
    "White-browed Bushchat": "IN",
    "Sichuan Partridge": "CN",
    "Hainan Partridge": "CN",
    "Przevalski's Partridge": "CN",
    "Chinese Monal": "CN",
    "Cabot's Tragopan": "CN",
    "Elliot's Pheasant": "CN",
    "Reeves's Pheasant": "CN",
    "Golden Pheasant": "CN",
    "Chinese Grouse": "CN",
    "Sichuan Jay": "CN",
    "Yellow-bellied Tit": "CN",
    "White-browed Tit": "CN",
    "Sichuan Tit": "CN",
    "Sooty Tit": "CN",
    "Silver-throated Tit": "CN",
    "Rufous-tailed Babbler": "CN",
    "Chinese Fulvetta": "CN",
    "Spectacled Fulvetta": "CN",
    "Three-toed Parrotbill": "CN",
    "Spectacled Parrotbill": "CN",
    "Rusty-throated Parrotbill": "CN",
    "Nonggang Babbler": "CN",
    "Huet's Fulvetta": "CN",
    "Barred Laughingthrush": "CN",
    "Giant Laughingthrush": "CN",
    "Snowy-cheeked Laughingthrush": "CN",
    "Giant Babax": "CN",
    "Tibetan Babax": "CN",
    "Buffy Laughingthrush": "CN",
    "Blue-crowned Laughingthrush": "CN",
    "Emei Shan Liocichla": "CN",
    "Sichuan Treecreeper": "CN",
    "Przevalski's Nuthatch": "CN",
    "Chinese Thrush": "CN",
    "Chinese Shortwing": "CN",
    "Ala Shan Redstart": "CN",
    "Tibetan Snowfinch": "CN",
    "Pink-rumped Rosefinch": "CN",
    "Chinese Beautiful Rosefinch": "CN",
    "Tibetan Rosefinch": "CN",
    "Sillem's Rosefinch": "CN",
    "Three-banded Rosefinch": "CN",
    "Chinese White-browed Rosefinch": "CN",
    "Great Spotted Kiwi": "NZ",
    "Little Spotted Kiwi": "NZ",
    "Southern Brown Kiwi": "NZ",
    "Paradise Shelduck": "NZ",
    "Blue Duck": "NZ",
    "New Zealand Scaup": "NZ",
    "Brown Teal": "NZ",
    "New Zealand Grebe": "NZ",
    "New Zealand Pigeon": "NZ",
    "Weka": "NZ",
    "South Island Takahe": "NZ",
    "Erect-crested Penguin": "NZ",
    "Yellow-eyed Penguin": "NZ",
    "Magenta Petrel": "NZ",
    "Spotted Shag": "NZ",
    "South Island Oystercatcher": "NZ",
    "Variable Oystercatcher": "NZ",
    "Black Stilt": "NZ",
    "Shore Plover": "NZ",
    "Wrybill": "NZ",
    "Snares Snipe": "NZ",
    "Black-billed Gull": "NZ",
    "Black-fronted Tern": "NZ",
    "New Zealand Falcon": "NZ",
    "Kakapo": "NZ",
    "Kea": "NZ",
    "New Zealand Kaka": "NZ",
    "Antipodes Parakeet": "NZ",
    "Malherbe's Parakeet": "NZ",
    "Reischek's Parakeet": "NZ",
    "Rifleman": "NZ",
    "Tui": "NZ",
    "New Zealand Bellbird": "NZ",
    "Whitehead": "NZ",
    "Yellowhead": "NZ",
    "Pipipi": "NZ",
    "New Zealand Fantail": "NZ",
    "North Island Kokako": "NZ",
    "South Island Kokako": "NZ",
    "North Island Saddleback": "NZ",
    "South Island Saddleback": "NZ",
    "Stitchbird": "NZ",
    "Black Robin": "NZ",
    "North Island Robin": "NZ",
    "South Island Robin": "NZ",
    "New Zealand Fernbird": "NZ",
    "New Zealand Pipit": "NZ",
    "Buff-headed Coucal": "SB",
    "Roviana Rail": "SB",
    "Makira Moorhen": "SB",
    "Yellow-bibbed Lory": "SB",
    "Makira Honeyeater": "SB",
    "Guadalcanal Honeyeater": "SB",
    "Black-headed Myzomela": "SB",
    "Sooty Myzomela": "SB",
    "Rennell Gerygone": "SB",
    "Guadalcanal Hooded Whistler": "SB",
    "Rennell Whistler": "SB",
    "Makira Cicadabird": "SB",
    "White-gorgeted Fantail": "SB",
    "Malaita Fantail": "SB",
    "Guadalcanal Fantail": "SB",
    "Dusky Fantail": "SB",
    "Rennell Fantail": "SB",
    "Malaita Monarch": "SB",
    "Kolombangara Monarch": "SB",
    "White-collared Monarch": "SB",
    "Vanikoro Monarch": "SB",
    "Rennell Shrikebill": "SB",
    "Chestnut-bellied Monarch": "SB",
    "White-capped Monarch": "SB",
    "Guadalcanal Thicketbird": "SB",
    "Bare-eyed White-eye": "SB",
    "Sanford's White-eye": "SB",
    "Rennell White-eye": "SB",
    "Ranongga White-eye": "SB",
    "Solomons White-eye": "SB",
    "Dark-eyed White-eye": "SB",
    "Kolombangara White-eye": "SB",
    "Malaita White-eye": "SB",
    "Santa Cruz White-eye": "SB",
    "Vanikoro White-eye": "SB",
    "Rennell Starling": "SB",
    "Makira Starling": "SB",
    "Guadalcanal Thrush": "SB",
    "Makira Thrush": "SB",
    "Mottled Flowerpecker": "SB",
    "Tepui Tinamou": "VE",
    "Merida Sunangel": "VE",
    "Venezuelan Sylph": "VE",
    "White-bearded Helmetcrest": "VE",
    "Green-tailed Emerald": "VE",
    "Scissor-tailed Hummingbird": "VE",
    "Rusty-flanked Crake": "VE",
    "Plain-flanked Rail": "VE",
    "Groove-billed Toucanet": "VE",
    "Venezuelan Parakeet": "VE",
    "Red-eared Parakeet": "VE",
    "Rose-headed Parakeet": "VE",
    "Great Antpitta": "VE",
    "Tachira Antpitta": "VE",
    "Scallop-breasted Antpitta": "VE",
    "Sucre Antpitta": "VE",
    "Merida Tapaculo": "VE",
    "Caracas Tapaculo": "VE",
    "Guttulate Foliage-gleaner": "VE",
    "White-throated Barbtail": "VE",
    "Ochre-browed Thistletail": "VE",
    "Orinoco Softtail": "VE",
    "Delta Amacuro Softtail": "VE",
    "Black-throated Spinetail": "VE",
    "Handsome Fruiteater": "VE",
    "Rufous-lored Tyrannulet": "VE",
    "Venezuelan Tyrannulet": "VE",
    "Urich's Tyrannulet": "VE",
    "Merida Wren": "VE",
    "Carrizal Seedeater": "VE",
    "Slaty-backed Hemispingus": "VE",
    "Venezuelan Flowerpiercer": "VE",
    "Merida Flowerpiercer": "VE",
    "Rufous-cheeked Tanager": "VE",
    "Hawaiian Goose": "US",
    "Laysan Duck": "US",
    "Hawaiian Duck": "US",
    "Hawaiian Coot": "US",
    "Hawaiian Hawk": "US",
    "Red-cockaded Woodpecker": "US",
    "Kauai Elepaio": "US",
    "Oahu Elepaio": "US",
    "Hawaii Elepaio": "US",
    "Yellow-billed Magpie": "US",
    "Hawaiian Crow": "US",
    "Carolina Chickadee": "US",
    "Millerbird": "US",
    "Brown-headed Nuthatch": "US",
    "Olomao": "US",
    "Omao": "US",
    "Puaiohi": "US",
    "Oahu Alauahio": "US",
    "Maui Alauahio": "US",
    "Akikiki": "US",
    "Laysan Finch": "US",
    "Nihoa Finch": "US",
    "Palila": "US",
    "Ou": "US",
    "Kauai Nukupuu": "US",
    "Maui Nukupuu": "US",
    "Akiapolaau": "US",
    "Maui Parrotbill": "US",
    "Anianiau": "US",
    "Hawaii Creeper": "US",
    "Akekee": "US",
    "Maui Akepa": "US",
    "Hawaii Akepa": "US",
    "Kauai Amakihi": "US",
    "Oahu Amakihi": "US",
    "Hawaii Amakihi": "US",
    "Iiwi": "US",
    "Apapane": "US",
    "Akohekohe": "US",
    "Cassia Crossbill": "US",
    "McKay's Bunting": "US",
    "Bachman's Sparrow": "US",
    "Seaside Sparrow": "US",
    "Saltmarsh Sparrow": "US",
    "Boat-tailed Grackle": "US",
    "Galapagos Dove": "EC",
    "Blue-throated Hillstar": "EC",
    "Violet-throated Metaltail": "EC",
    "Black-breasted Puffleg": "EC",
    "Turquoise-throated Puffleg": "EC",
    "Esmeraldas Woodstar": "EC",
    "Galapagos Rail": "EC",
    "Galapagos Penguin": "EC",
    "Flightless Cormorant": "EC",
    "Lava Gull": "EC",
    "Galapagos Hawk": "EC",
    "Lilacine Amazon": "EC",
    "El Oro Parakeet": "EC",
    "Ecuadorian Tapaculo": "EC",
    "Galapagos Flycatcher": "EC",
    "Galapagos Martin": "EC",
    "Floreana Mockingbird": "EC",
    "Galapagos Mockingbird": "EC",
    "Española Mockingbird": "EC",
    "San Cristobal Mockingbird": "EC",
    "Vegetarian Finch": "EC",
    "Mangrove Finch": "EC",
    "Woodpecker Finch": "EC",
    "Tanzanian Red-billed Hornbill": "TZ",
    "Yellow-collared Lovebird": "TZ",
    "Usambara Hyliota": "TZ",
    "Beesley's Lark": "TZ",
    "Yellow-throated Mountain Greenbul": "TZ",
    "Uluguru Mountain Greenbul": "TZ",
    "South Pare White-eye": "TZ",
    "Kilimanjaro White-eye": "TZ",
    "Pemba White-eye": "TZ",
    "Ashy Starling": "TZ",
    "Usambara Thrush": "TZ",
    "Usambara Akalat": "TZ",
    "Iringa Akalat": "TZ",
    "Rubeho Akalat": "TZ",
    "Banded Sunbird": "TZ",
    "Moreau's Sunbird": "TZ",
    "Loveridge's Sunbird": "TZ",
    "Pemba Sunbird": "TZ",
    "Rufous-winged Sunbird": "TZ",
    "Kilombero Weaver": "TZ",
    "Usambara Weaver": "TZ",
    "Kipengere Seedeater": "TZ",
    "Orange Dove": "FJ",
    "Golden Dove": "FJ",
    "Whistling Dove": "FJ",
    "Fiji Petrel": "FJ",
    "Fiji Goshawk": "FJ",
    "Red-throated Lorikeet": "FJ",
    "Collared Lory": "FJ",
    "Kadavu Honeyeater": "FJ",
    "Rotuma Myzomela": "FJ",
    "Fiji Woodswallow": "FJ",
    "Natewa Silktail": "FJ",
    "Taveuni Silktail": "FJ",
    "Fiji Streaked Fantail": "FJ",
    "Kadavu Fantail": "FJ",
    "Chestnut-throated Flycatcher": "FJ",
    "Azure-crested Flycatcher": "FJ",
    "Ogea Monarch": "FJ",
    "Slaty Monarch": "FJ",
    "Black-throated Shrikebill": "FJ",
    "Long-legged Thicketbird": "FJ",
    "Fiji White-eye": "FJ",
    "Fiji Parrotfinch": "FJ",
    "Pink-billed Parrotfinch": "FJ",
    "Sri Lanka Spurfowl": "LK",
    "Sri Lanka Junglefowl": "LK",
    "Green-billed Coucal": "LK",
    "Red-faced Malkoha": "LK",
    "Chestnut-backed Owlet": "LK",
    "Yellow-fronted Barbet": "LK",
    "Sri Lanka Woodshrike": "LK",
    "Sri Lanka Drongo": "LK",
    "Sri Lanka Swallow": "LK",
    "Black-capped Bulbul": "LK",
    "Yellow-eared Bulbul": "LK",
    "Sri Lanka White-eye": "LK",
    "Brown-capped Babbler": "LK",
    "Orange-billed Babbler": "LK",
    "Ashy-headed Laughingthrush": "LK",
    "White-faced Starling": "LK",
    "Sri Lanka Thrush": "LK",
    "Spot-winged Thrush": "LK",
    "Dull-blue Flycatcher": "LK",
    "White-throated Flowerpecker": "LK",
    "Tahiti Swiftlet": "PF",
    "Rapa Shearwater": "PF",
    "Tuamotu Sandpiper": "PF",
    "Ultramarine Lorikeet": "PF",
    "Tahiti Monarch": "PF",
    "Iphis Monarch": "PF",
    "Fatu Hiva Monarch": "PF",
    "Ua Pou Monarch": "PF",
    "Tahiti Swallow": "PF",
    "Ring-tailed Pigeon": "JM",
    "Jamaican Mango": "JM",
    "Red-billed Streamertail": "JM",
    "Black-billed Streamertail": "JM",
    "Chestnut-bellied Cuckoo": "JM",
    "Jamaican Owl": "JM",
    "Jamaican Tody": "JM",
    "Jamaican Woodpecker": "JM",
    "Black-billed Amazon": "JM",
    "Yellow-billed Amazon": "JM",
    "Jamaican Becard": "JM",
    "Sad Flycatcher": "JM",
    "Rufous-tailed Flycatcher": "JM",
    "Jamaican Pewee": "JM",
    "Blue Mountain Vireo": "JM",
    "Jamaican Vireo": "JM",
    "Jamaican Crow": "JM",
    "White-eyed Thrush": "JM",
    "White-chinned Thrush": "JM",
    "Jamaican Euphonia": "JM",
    "Jamaican Blackbird": "JM",
    "Arrowhead Warbler": "JM",
    "Jamaican Spindalis": "JM",
    "Orangequit": "JM",
    "Yellow-shouldered Grassquit": "JM",
    "Cuban Nightjar": "CU",
    "Bee Hummingbird": "CU",
    "Zapata Rail": "CU",
    "Cuban Kite": "CU",
    "Gundlach's Hawk": "CU",
    "Cuban Black Hawk": "CU",
    "Cuban Trogon": "CU",
    "Cuban Tody": "CU",
    "Fernandina's Flicker": "CU",
    "Cuban Green Woodpecker": "CU",
    "Cuban Parakeet": "CU",
    "Giant Kingbird": "CU",
    "Cuban Vireo": "CU",
    "Cuban Gnatcatcher": "CU",
    "Zapata Wren": "CU",
    "Cuban Solitaire": "CU",
    "Zapata Sparrow": "CU",
    "Yellow-headed Warbler": "CU",
    "Oriente Warbler": "CU",
    "Cuban Oriole": "CU",
    "Red-shouldered Blackbird": "CU",
    "Cuban Blackbird": "CU",
    "Cuban Bullfinch": "CU",
    "Cuban Grassquit": "CU",
    "Taiwan Partridge": "TW",
    "Mikado Pheasant": "TW",
    "Swinhoe's Pheasant": "TW",
    "Taiwan Barbet": "TW",
    "Chestnut-bellied Tit": "TW",
    "Taiwan Cupwing": "TW",
    "Styan's Bulbul": "TW",
    "Taiwan Fulvetta": "TW",
    "Taiwan Yuhina": "TW",
    "Taiwan Hwamei": "TW",
    "Rufous-crowned Laughingthrush": "TW",
    "Rusty Laughingthrush": "TW",
    "White-whiskered Laughingthrush": "TW",
    "White-eared Sibia": "TW",
    "Taiwan Liocichla": "TW",
    "Taiwan Barwing": "TW",
    "Taiwan Thrush": "TW",
    "Taiwan Shortwing": "TW",
    "Flamecrest": "TW",
    "Taiwan Rosefinch": "TW",
    "Sao Tome Spinetail": "TW",
    "Newton's Fiscal": "TW",
    "Sao Tome Prinia": "TW",
    "Principe White-eye": "TW",
    "Sao Tome White-eye": "TW",
    "Black-capped Speirops": "TW",
    "Principe Speirops": "TW",
    "Principe Starling": "TW",
    "Principe Thrush": "TW",
    "Sao Tome Thrush": "TW",
    "Principe Sunbird": "TW",
    "Newton's Sunbird": "TW",
    "Giant Weaver": "TW",
    "Sao Tome Weaver": "TW",
    "Sao Tome Short-tail": "TW",
    "Principe Seedeater": "TW",
    "Sao Tome Grosbeak": "TW",
    "Kagu": "NC",
    "Cloven-feathered Dove": "NC",
    "New Caledonian Nightjar": "NC",
    "New Caledonian Owlet-nightjar": "NC",
    "New Caledonian Rail": "NC",
    "New Caledonian Buttonquail": "NC",
    "Horned Parakeet": "NC",
    "Ouvea Parakeet": "NC",
    "New Caledonian Parakeet": "NC",
    "New Caledonian Lorikeet": "NC",
    "Crow Honeyeater": "NC",
    "New Caledonian Friarbird": "NC",
    "New Caledonian Myzomela": "NC",
    "Barred Honeyeater": "NC",
    "New Caledonian Whistler": "NC",
    "New Caledonian Crow": "NC",
    "New Caledonian Thicketbird": "NC",
    "Large Lifou White-eye": "NC",
    "Green-backed White-eye": "NC",
    "Small Lifou White-eye": "NC",
    "Striated Starling": "NC",
    "Red-throated Parrotfinch": "NC",
    "Comoro Cuckooshrike": "KM",
    "Comoro Blue Vanga": "KM",
    "Moheli Bulbul": "KM",
    "Moheli White-eye": "KM",
    "Kirk's White-eye": "KM",
    "Anjouan White-eye": "KM",
    "Comoro Thrush": "KM",
    "Humblot's Sunbird": "KM",
    "Anjouan Sunbird": "KM",
    "Pohnpei Kingfisher": "FM",
    "Pohnpei Lorikeet": "FM",
    "Yap Cicadabird": "FM",
    "Pohnpei Cicadabird": "FM",
    "Pohnpei Fantail": "FM",
    "Chuuk Flycatcher": "FM",
    "Pohnpei Flycatcher": "FM",
    "Yap Monarch": "FM",
    "Chuuk Monarch": "FM",
    "Teardrop White-eye": "FM",
    "Long-billed White-eye": "FM",
    "Pohnpei White-eye": "FM",
    "Kosrae White-eye": "FM",
    "Pohnpei Starling": "FM",
    "Copper Pheasant": "JP",
    "Green Pheasant": "JP",
    "Okinawa Rail": "JP",
    "Bannerman's Shearwater": "JP",
    "Amami Woodcock": "JP",
    "Japanese Woodpecker": "JP",
    "Okinawa Woodpecker": "JP",
    "Ryukyu Minivet": "JP",
    "Iriomote Tit": "JP",
    "Bonin White-eye": "JP",
    "Amami Thrush": "JP",
    "Izu Thrush": "JP",
    "Izu Robin": "JP",
    "Ryukyu Robin": "JP",
    "Okinawa Robin": "JP",
    "Ryukyu Flycatcher": "JP",
    "Red-crested Turaco": "AO",
    "Red-backed Mousebird": "AO",
    "White-fronted Wattle-eye": "AO",
    "Pulitzer's Longbill": "AO",
    "Hartert's Camaroptera": "AO",
    "Huambo Cisticola": "AO",
    "Angola Greenbul": "AO",
    "Gabela Akalat": "AO",
    "Montane Double-collared Sunbird": "AO",
    "Angola Waxbill": "AO",
    "Moorland Francolin": "ET",
    "Blue-winged Goose": "ET",
    "Nechisar Nightjar": "ET",
    "Spot-breasted Lapwing": "ET",
    "Yellow-fronted Parrot": "ET",
    "Ethiopian Bushcrow": "ET",
    "White-tailed Swallow": "ET",
    "Abyssinian Catbird": "ET",
    "Red-billed Pytilia": "ET",
    "Abyssinian Longclaw": "ET",
    "Horned Curassow": "BO",
    "Coppery Thorntail": "BO",
    "Black-hooded Sunbeam": "BO",
    "Cliff Parakeet": "BO",
    "Blue-throated Macaw": "BO",
    "Red-fronted Macaw": "BO",
    "Masked Antpitta": "BO",
    "Berlepsch's Canastero": "BO",
    "Black-throated Thistletail": "BO",
    "Bolivian Spinetail": "BO",
    "Unicolored Thrush": "BO",
    "Bolivian Blackbird": "BO",
    "Forest Buzzard": "ZA",
    "Knysna Woodpecker": "ZA",
    "Cape Parrot": "ZA",
    "Cape Rockjumper": "ZA",
    "Karoo Lark": "ZA",
    "Red Lark": "ZA",
    "Rudd's Lark": "ZA",
    "Botha's Lark": "ZA",
    "Victorin's Warbler": "ZA",
    "Knysna Warbler": "ZA",
    "Cape Bulbul": "ZA",
    "Cape Sugarbird": "ZA",
    "Orange-breasted Sunbird": "ZA",
    "Protea Canary": "ZA",
    "Cape Siskin": "ZA",
    "Grauer's Cuckooshrike": "CD",
    "Yellow-crested Helmetshrike": "CD",
    "Kabobo Apalis": "CD",
    "Prigogine's Greenbul": "CD",
    "Rockefeller's Sunbird": "CD",
    "Yellow-legged Weaver": "CD",
    "Black-lored Waxbill": "CD",
    "Hooded Grebe": "AR",
    "Sandy Gallito": "AR",
    "White-browed Tapaculo": "AR",
    "Cordoba Cinclodes": "AR",
    "Olrog's Cinclodes": "AR",
    "Patagonian Canastero": "AR",
    "Steinbach's Canastero": "AR",
    "White-throated Cacholote": "AR",
    "Salinas Monjita": "AR",
    "Rusty-backed Monjita": "AR",
    "Puerto Rican Nightjar": "PR",
    "Green Mango": "PR",
    "Puerto Rican Emerald": "PR",
    "Puerto Rican Tody": "PR",
    "Puerto Rican Woodpecker": "PR",
    "Puerto Rican Amazon": "PR",
    "Puerto Rican Vireo": "PR",
    "Puerto Rican Euphonia": "PR",
    "Puerto Rican Oriole": "PR",
    "Yellow-shouldered Blackbird": "PR",
    "Adelaide's Warbler": "PR",
    "Puerto Rican Spindalis": "PR",
    "Puerto Rican Tanager": "PR",
    "Puerto Rican Bullfinch": "PR",
    "Seychelles Warbler": "PR",
    "Seychelles Bulbul": "PR",
    "Seychelles White-eye": "PR",
    "Aldabra White-eye": "PR",
    "Chilean Tinamou": "CL",
    "Juan Fernandez Firecrown": "CL",
    "Chilean Woodstar": "CL",
    "Slender-billed Parakeet": "CL",
    "Moustached Turca": "CL",
    "White-throated Tapaculo": "CL",
    "Dusky Tapaculo": "CL",
    "Seaside Cinclodes": "CL",
    "Masafuera Rayadito": "CL",
    "Dusky-tailed Canastero": "CL",
    "Palau Nightjar": "PW",
    "Palau Swiftlet": "PW",
    "Palau Kingfisher": "PW",
    "Morningbird": "PW",
    "Palau Cicadabird": "PW",
    "Palau Fantail": "PW",
    "Palau Flycatcher": "PW",
    "Giant White-eye": "PW",
    "Dusky White-eye": "PW",
    "Williams's Lark": "KE",
    "Taita Apalis": "KE",
    "Tana River Cisticola": "KE",
    "Aberdare Cisticola": "KE",
    "Taita White-eye": "KE",
    "Kikuyu White-eye": "KE",
    "Taita Thrush": "KE",
    "Sharpe's Longclaw": "KE",
    "Jerdon's Minivet": "MM",
    "Hooded Treepie": "MM",
    "Burmese Bushlark": "MM",
    "Burmese Prinia": "MM",
    "Pale-eyed Bulbul": "MM",
    "Ayeyarwady Bulbul": "MM",
    "White-throated Babbler": "MM",
    "White-browed Nuthatch": "MM",
    "Socotra Buzzard": "YE",
    "Socotra Warbler": "YE",
    "Socotra Cisticola": "YE",
    "Socotra Starling": "YE",
    "Socotra Sunbird": "YE",
    "Socotra Sparrow": "YE",
    "Abd al Kuri Sparrow": "YE",
    "Socotra Grosbeak": "YE",
    "Socotra Bunting": "YE",
    "Annam Prinia": "VN",
    "Black-crowned Fulvetta": "VN",
    "Orange-breasted Laughingthrush": "VN",
    "Golden-winged Laughingthrush": "VN",
    "Collared Laughingthrush": "VN",
    "Vietnamese Greenfinch": "VN",
    "Pink Pigeon": "MU",
    "Mauritius Kestrel": "MU",
    "Echo Parakeet": "MU",
    "Mauritius Cuckooshrike": "MU",
    "Rodrigues Warbler": "MU",
    "Mauritius Bulbul": "MU",
    "Mauritius Fody": "MU",
    "Rodrigues Fody": "MU",
    "Somali Pigeon": "MU",
    "Sabah Partridge": "MY",
    "Dulit Partridge": "MY",
    "Bornean Swiftlet": "MY",
    "Black-crowned Pitta": "MY",
    "Tooth-billed Pigeon": "WS",
    "Samoan Moorhen": "WS",
    "Flat-billed Kingfisher": "WS",
    "Mao": "WS",
    "Samoan Whistler": "WS",
    "Samoan Triller": "WS",
    "Samoan Fantail": "WS",
    "Samoan Flycatcher": "WS",
    "Samoan White-eye": "WS",
    "Coppery-headed Emerald": "CR",
    "Mangrove Hummingbird": "CR",
    "Cocos Cuckoo": "CR",
    "Cocos Finch": "CR",
    "Gough Moorhen": "SH",
    "Ascension Frigatebird": "SH",
    "Tristan Thrush": "SH",
    "Wilkins's Finch": "SH",
    "Inagua Woodstar": "BS",
    "Bahama Swallow": "BS",
    "Bahama Nuthatch": "BS",
    "Bahama Oriole": "BS",
    "Bahama Yellowthroat": "BS",
    "Bahama Warbler": "BS",
    "Glow-throated Hummingbird": "PA",
    "Stripe-cheeked Woodpecker": "PA",
    "Coiba Spinetail": "PA",
    "Yellow-green Tyrannulet": "PA",
    "Mariana Kingfisher": "MP",
    "Tinian Monarch": "MP",
    "Mariana Crow": "MP",
    "Canary Islands Chiffchaff": "ES",
    "Balearic Warbler": "ES",
    "Fuerteventura Stonechat": "ES",
    "Tenerife Blue Chaffinch": "ES",
    "Gran Canaria Blue Chaffinch": "ES",
    "Mascarene Petrel": "ES",
    "Reunion Bulbul": "ES",
    "Reunion Stonechat": "ES",
    "Semper's Warbler": "LC",
    "Cape Verde Sparrow": "CV",
    "Bannerman's Turaco": "CM",
    "Banded Wattle-eye": "CM",
    "Bates's Weaver": "CM",
    "Bioko Batis": "GQ",
    "Annobon White-eye": "GQ",
    "Bioko Speirops": "GQ",
    "Norfolk Island Parakeet": "NF",
    "Norfolk Robin": "NF",
    "Slender-billed White-eye": "NF",
    "White-chested White-eye": "NF",
    "Mayotte Drongo": "YT",
    "Mayotte Sunbird": "YT",
    "Blackish Cinclodes": "FK",
    "Cobb's Wren": "FK",
    "Whistling Warbler": "VC",
    "Trinidad Motmot": "TT",
    "Black-cheeked Lovebird": "ZM",
    "Chestnut-headed Partridge": "KH",
    "Cambodian Tailorbird": "KH",
    "Cambodian Laughingthrush": "KH",
    "Turquoise-throated Barbet": "TH",
    "Amsterdam Albatross": "TF",
    "Red-necked Amazon": "DM",
    "Imperial Amazon": "DM",
    "Ridgway's Hawk": "DO",
    "Grenada Dove": "GD",
    "Siberian Grouse": "RU",
    "Siberian Nuthatch": "RU",
    "Namuli Apalis": "MZ",
    "Guam Rail": "GU",
    "Guam Kingfisher": "GU",
    "Tongan Whistler": "TO",
    "Barbuda Warbler": "TO",
    "Grand Cayman Bullfinch": "TO",
    "Guadeloupe Woodpecker": "TO",
    "Honduran Emerald": "TO",
    "Montserrat Oriole": "TO",
    "Algerian Nuthatch": "TO",
    "Scottish Crossbill": "TO",
    "Dune Lark": "TO",
    "Fox's Weaver": "TO",
    "Spiny Babbler": "TO"
}
